{
 "cols": [
  {
   "is_class": false,
   "is_explicit": false,
   "module": "builtins",
   "module_short": "builtins",
   "name": "list"
  }
 ],
 "dc.Liver": [
  {
   "is_class": true,
   "is_explicit": false,
   "module": "dcmri.ui_liver",
   "module_short": "dcmri",
   "name": "Liver"
  },
  {
   "is_class": true,
   "is_explicit": false,
   "module": "dcmri",
   "module_short": "dcmri",
   "name": "Liver"
  },
  {
   "is_class": true,
   "is_explicit": false,
   "module": "dcmri.ui",
   "module_short": "dcmri",
   "name": "Model"
  },
  {
   "is_class": true,
   "is_explicit": false,
   "module": "dcmri",
   "module_short": "dcmri",
   "name": "Model"
  },
  {
   "is_class": false,
   "is_explicit": false,
   "module": "dcmri",
   "module_short": "dcmri",
   "name": "Liver"
  }
 ],
 "dc.aif_tristan_rat": [
  {
   "is_class": false,
   "is_explicit": false,
   "module": "builtins",
   "module_short": "builtins",
   "name": "function"
  },
  {
   "is_class": false,
   "is_explicit": false,
   "module": "dcmri",
   "module_short": "dcmri",
   "name": "aif_tristan_rat"
  }
 ],
 "dc.fetch": [
  {
   "is_class": false,
   "is_explicit": false,
   "module": "builtins",
   "module_short": "builtins",
   "name": "function"
  },
  {
   "is_class": false,
   "is_explicit": false,
   "module": "dcmri",
   "module_short": "dcmri",
   "name": "fetch"
  }
 ],
 "dc.read_dmr": [
  {
   "is_class": false,
   "is_explicit": false,
   "module": "builtins",
   "module_short": "builtins",
   "name": "function"
  },
  {
   "is_class": false,
   "is_explicit": false,
   "module": "dcmri",
   "module_short": "dcmri",
   "name": "read_dmr"
  }
 ],
 "dcmri.Liver": [
  {
   "is_class": false,
   "is_explicit": true,
   "module": "dcmri",
   "module_short": "dcmri",
   "name": "Liver"
  }
 ],
 "dmr": [
  {
   "is_class": false,
   "is_explicit": false,
   "module": "builtins",
   "module_short": "builtins",
   "name": "dict"
  }
 ],
 "dmrfile": [
  {
   "is_class": false,
   "is_explicit": false,
   "module": "builtins",
   "module_short": "builtins",
   "name": "str"
  }
 ],
 "filtered_data": [
  {
   "is_class": false,
   "is_explicit": false,
   "module": "pandas.core.frame",
   "module_short": "pandas.core.frame",
   "name": "DataFrame"
  },
  {
   "is_class": false,
   "is_explicit": false,
   "module": "pandas.core",
   "module_short": "pandas.core",
   "name": "DataFrame"
  },
  {
   "is_class": false,
   "is_explicit": false,
   "module": "pandas",
   "module_short": "pandas",
   "name": "DataFrame"
  }
 ],
 "g": [
  {
   "is_class": false,
   "is_explicit": false,
   "module": "seaborn.axisgrid",
   "module_short": "seaborn",
   "name": "FacetGrid"
  },
  {
   "is_class": false,
   "is_explicit": false,
   "module": "seaborn",
   "module_short": "seaborn",
   "name": "FacetGrid"
  }
 ],
 "g.axes": [
  {
   "is_class": false,
   "is_explicit": false,
   "module": "seaborn.axisgrid",
   "module_short": "seaborn",
   "name": "FacetGrid.axes"
  },
  {
   "is_class": false,
   "is_explicit": false,
   "module": "seaborn",
   "module_short": "seaborn",
   "name": "FacetGrid.axes"
  },
  {
   "is_class": false,
   "is_explicit": false,
   "module": "seaborn.axisgrid",
   "module_short": "seaborn.axisgrid",
   "name": "Grid.axes"
  },
  {
   "is_class": false,
   "is_explicit": false,
   "module": "seaborn",
   "module_short": "seaborn",
   "name": "Grid.axes"
  },
  {
   "is_class": false,
   "is_explicit": false,
   "module": "seaborn.axisgrid",
   "module_short": "seaborn.axisgrid",
   "name": "_BaseGrid.axes"
  },
  {
   "is_class": false,
   "is_explicit": false,
   "module": "seaborn",
   "module_short": "seaborn",
   "name": "_BaseGrid.axes"
  }
 ],
 "g.set_titles": [
  {
   "is_class": false,
   "is_explicit": false,
   "module": "seaborn.axisgrid",
   "module_short": "seaborn",
   "name": "FacetGrid.set_titles"
  },
  {
   "is_class": false,
   "is_explicit": false,
   "module": "seaborn",
   "module_short": "seaborn",
   "name": "FacetGrid.set_titles"
  },
  {
   "is_class": false,
   "is_explicit": false,
   "module": "seaborn.axisgrid",
   "module_short": "seaborn.axisgrid",
   "name": "Grid.set_titles"
  },
  {
   "is_class": false,
   "is_explicit": false,
   "module": "seaborn",
   "module_short": "seaborn",
   "name": "Grid.set_titles"
  },
  {
   "is_class": false,
   "is_explicit": false,
   "module": "seaborn.axisgrid",
   "module_short": "seaborn.axisgrid",
   "name": "_BaseGrid.set_titles"
  },
  {
   "is_class": false,
   "is_explicit": false,
   "module": "seaborn",
   "module_short": "seaborn",
   "name": "_BaseGrid.set_titles"
  }
 ],
 "g.set_ylabels": [
  {
   "is_class": false,
   "is_explicit": false,
   "module": "seaborn.axisgrid",
   "module_short": "seaborn",
   "name": "FacetGrid.set_ylabels"
  },
  {
   "is_class": false,
   "is_explicit": false,
   "module": "seaborn",
   "module_short": "seaborn",
   "name": "FacetGrid.set_ylabels"
  },
  {
   "is_class": false,
   "is_explicit": false,
   "module": "seaborn.axisgrid",
   "module_short": "seaborn.axisgrid",
   "name": "Grid.set_ylabels"
  },
  {
   "is_class": false,
   "is_explicit": false,
   "module": "seaborn",
   "module_short": "seaborn",
   "name": "Grid.set_ylabels"
  },
  {
   "is_class": false,
   "is_explicit": false,
   "module": "seaborn.axisgrid",
   "module_short": "seaborn.axisgrid",
   "name": "_BaseGrid.set_ylabels"
  },
  {
   "is_class": false,
   "is_explicit": false,
   "module": "seaborn",
   "module_short": "seaborn",
   "name": "_BaseGrid.set_ylabels"
  }
 ],
 "https://orcid.org/0000-0002-5608-9812": [
  {
   "is_class": false,
   "is_explicit": true,
   "module": "https://orcid",
   "module_short": "https://orcid",
   "name": "org/0000-0002-5608-9812"
  }
 ],
 "https://www.imi-tristan.eu/liver": [
  {
   "is_class": false,
   "is_explicit": true,
   "module": "https://www.imi-tristan",
   "module_short": "https://www.imi-tristan",
   "name": "eu/liver"
  }
 ],
 "i": [
  {
   "is_class": false,
   "is_explicit": false,
   "module": "builtins",
   "module_short": "builtins",
   "name": "int"
  }
 ],
 "model": [
  {
   "is_class": false,
   "is_explicit": false,
   "module": "dcmri.ui_liver",
   "module_short": "dcmri",
   "name": "Liver"
  },
  {
   "is_class": false,
   "is_explicit": false,
   "module": "dcmri",
   "module_short": "dcmri",
   "name": "Liver"
  }
 ],
 "model.export_params": [
  {
   "is_class": false,
   "is_explicit": false,
   "module": "dcmri.ui_liver",
   "module_short": "dcmri",
   "name": "Liver.export_params"
  },
  {
   "is_class": false,
   "is_explicit": false,
   "module": "dcmri",
   "module_short": "dcmri",
   "name": "Liver.export_params"
  },
  {
   "is_class": false,
   "is_explicit": false,
   "module": "dcmri.ui",
   "module_short": "dcmri",
   "name": "Model.export_params"
  },
  {
   "is_class": false,
   "is_explicit": false,
   "module": "dcmri",
   "module_short": "dcmri",
   "name": "Model.export_params"
  }
 ],
 "model.plot": [
  {
   "is_class": false,
   "is_explicit": false,
   "module": "dcmri.ui_liver",
   "module_short": "dcmri",
   "name": "Liver.plot"
  },
  {
   "is_class": false,
   "is_explicit": false,
   "module": "dcmri",
   "module_short": "dcmri",
   "name": "Liver.plot"
  },
  {
   "is_class": false,
   "is_explicit": false,
   "module": "dcmri.ui",
   "module_short": "dcmri",
   "name": "Model.plot"
  },
  {
   "is_class": false,
   "is_explicit": false,
   "module": "dcmri",
   "module_short": "dcmri",
   "name": "Model.plot"
  }
 ],
 "model.print_params": [
  {
   "is_class": false,
   "is_explicit": false,
   "module": "dcmri.ui_liver",
   "module_short": "dcmri",
   "name": "Liver.print_params"
  },
  {
   "is_class": false,
   "is_explicit": false,
   "module": "dcmri",
   "module_short": "dcmri",
   "name": "Liver.print_params"
  },
  {
   "is_class": false,
   "is_explicit": false,
   "module": "dcmri.ui",
   "module_short": "dcmri",
   "name": "Model.print_params"
  },
  {
   "is_class": false,
   "is_explicit": false,
   "module": "dcmri",
   "module_short": "dcmri",
   "name": "Model.print_params"
  }
 ],
 "model.train": [
  {
   "is_class": false,
   "is_explicit": false,
   "module": "dcmri.ui_liver",
   "module_short": "dcmri",
   "name": "Liver.train"
  },
  {
   "is_class": false,
   "is_explicit": false,
   "module": "dcmri",
   "module_short": "dcmri",
   "name": "Liver.train"
  },
  {
   "is_class": false,
   "is_explicit": false,
   "module": "dcmri.ui",
   "module_short": "dcmri",
   "name": "Model.train"
  },
  {
   "is_class": false,
   "is_explicit": false,
   "module": "dcmri",
   "module_short": "dcmri",
   "name": "Model.train"
  }
 ],
 "np.amax": [
  {
   "is_class": false,
   "is_explicit": false,
   "module": "numpy",
   "module_short": "numpy",
   "name": "_ArrayFunctionDispatcher"
  },
  {
   "is_class": false,
   "is_explicit": false,
   "module": "numpy",
   "module_short": "numpy",
   "name": "amax"
  }
 ],
 "np.arange": [
  {
   "is_class": false,
   "is_explicit": false,
   "module": "builtins",
   "module_short": "builtins",
   "name": "builtin_function_or_method"
  },
  {
   "is_class": false,
   "is_explicit": false,
   "module": "numpy",
   "module_short": "numpy",
   "name": "arange"
  }
 ],
 "par": [
  {
   "is_class": false,
   "is_explicit": false,
   "module": "builtins",
   "module_short": "builtins",
   "name": "dict"
  }
 ],
 "pars": [
  {
   "is_class": false,
   "is_explicit": false,
   "module": "builtins",
   "module_short": "builtins",
   "name": "dict"
  }
 ],
 "pd.DataFrame": [
  {
   "is_class": true,
   "is_explicit": false,
   "module": "pandas.core.frame",
   "module_short": "pandas.core.frame",
   "name": "DataFrame"
  },
  {
   "is_class": true,
   "is_explicit": false,
   "module": "pandas.core",
   "module_short": "pandas.core",
   "name": "DataFrame"
  },
  {
   "is_class": true,
   "is_explicit": false,
   "module": "pandas",
   "module_short": "pandas",
   "name": "DataFrame"
  },
  {
   "is_class": true,
   "is_explicit": false,
   "module": "pandas.core.generic",
   "module_short": "pandas.core.generic",
   "name": "NDFrame"
  },
  {
   "is_class": true,
   "is_explicit": false,
   "module": "pandas.core",
   "module_short": "pandas.core",
   "name": "NDFrame"
  },
  {
   "is_class": true,
   "is_explicit": false,
   "module": "pandas",
   "module_short": "pandas",
   "name": "NDFrame"
  },
  {
   "is_class": true,
   "is_explicit": false,
   "module": "pandas.core.arraylike",
   "module_short": "pandas.core.arraylike",
   "name": "OpsMixin"
  },
  {
   "is_class": true,
   "is_explicit": false,
   "module": "pandas.core",
   "module_short": "pandas.core",
   "name": "OpsMixin"
  },
  {
   "is_class": true,
   "is_explicit": false,
   "module": "pandas",
   "module_short": "pandas",
   "name": "OpsMixin"
  },
  {
   "is_class": true,
   "is_explicit": false,
   "module": "pandas.core.base",
   "module_short": "pandas.core.base",
   "name": "PandasObject"
  },
  {
   "is_class": true,
   "is_explicit": false,
   "module": "pandas.core",
   "module_short": "pandas.core",
   "name": "PandasObject"
  },
  {
   "is_class": true,
   "is_explicit": false,
   "module": "pandas",
   "module_short": "pandas",
   "name": "PandasObject"
  },
  {
   "is_class": true,
   "is_explicit": false,
   "module": "pandas.core.indexing",
   "module_short": "pandas.core.indexing",
   "name": "IndexingMixin"
  },
  {
   "is_class": true,
   "is_explicit": false,
   "module": "pandas.core",
   "module_short": "pandas.core",
   "name": "IndexingMixin"
  },
  {
   "is_class": true,
   "is_explicit": false,
   "module": "pandas",
   "module_short": "pandas",
   "name": "IndexingMixin"
  },
  {
   "is_class": true,
   "is_explicit": false,
   "module": "pandas.core.accessor",
   "module_short": "pandas.core.accessor",
   "name": "DirNamesMixin"
  },
  {
   "is_class": true,
   "is_explicit": false,
   "module": "pandas.core",
   "module_short": "pandas.core",
   "name": "DirNamesMixin"
  },
  {
   "is_class": true,
   "is_explicit": false,
   "module": "pandas",
   "module_short": "pandas",
   "name": "DirNamesMixin"
  },
  {
   "is_class": false,
   "is_explicit": false,
   "module": "pandas",
   "module_short": "pandas",
   "name": "DataFrame"
  }
 ],
 "plt.rc": [
  {
   "is_class": false,
   "is_explicit": false,
   "module": "builtins",
   "module_short": "builtins",
   "name": "function"
  },
  {
   "is_class": false,
   "is_explicit": false,
   "module": "matplotlib.pyplot",
   "module_short": "matplotlib.pyplot",
   "name": "rc"
  }
 ],
 "plt.rcParams": [
  {
   "is_class": false,
   "is_explicit": false,
   "module": "matplotlib",
   "module_short": "matplotlib",
   "name": "RcParams"
  },
  {
   "is_class": false,
   "is_explicit": false,
   "module": "matplotlib.pyplot",
   "module_short": "matplotlib",
   "name": "rcParams"
  }
 ],
 "plt.show": [
  {
   "is_class": false,
   "is_explicit": false,
   "module": "builtins",
   "module_short": "builtins",
   "name": "function"
  },
  {
   "is_class": false,
   "is_explicit": false,
   "module": "matplotlib.pyplot",
   "module_short": "matplotlib.pyplot",
   "name": "show"
  }
 ],
 "plt.tight_layout": [
  {
   "is_class": false,
   "is_explicit": false,
   "module": "builtins",
   "module_short": "builtins",
   "name": "function"
  },
  {
   "is_class": false,
   "is_explicit": false,
   "module": "matplotlib.pyplot",
   "module_short": "matplotlib.pyplot",
   "name": "tight_layout"
  }
 ],
 "results": [
  {
   "is_class": false,
   "is_explicit": false,
   "module": "pandas.core.frame",
   "module_short": "pandas.core.frame",
   "name": "DataFrame"
  },
  {
   "is_class": false,
   "is_explicit": false,
   "module": "pandas.core",
   "module_short": "pandas.core",
   "name": "DataFrame"
  },
  {
   "is_class": false,
   "is_explicit": false,
   "module": "pandas",
   "module_short": "pandas",
   "name": "DataFrame"
  }
 ],
 "results.query": [
  {
   "is_class": false,
   "is_explicit": false,
   "module": "pandas.core.frame",
   "module_short": "pandas.core.frame",
   "name": "DataFrame.query"
  },
  {
   "is_class": false,
   "is_explicit": false,
   "module": "pandas.core",
   "module_short": "pandas.core",
   "name": "DataFrame.query"
  },
  {
   "is_class": false,
   "is_explicit": false,
   "module": "pandas",
   "module_short": "pandas",
   "name": "DataFrame.query"
  },
  {
   "is_class": false,
   "is_explicit": false,
   "module": "pandas.core.generic",
   "module_short": "pandas.core.generic",
   "name": "NDFrame.query"
  },
  {
   "is_class": false,
   "is_explicit": false,
   "module": "pandas.core",
   "module_short": "pandas.core",
   "name": "NDFrame.query"
  },
  {
   "is_class": false,
   "is_explicit": false,
   "module": "pandas",
   "module_short": "pandas",
   "name": "NDFrame.query"
  },
  {
   "is_class": false,
   "is_explicit": false,
   "module": "pandas.core.arraylike",
   "module_short": "pandas.core.arraylike",
   "name": "OpsMixin.query"
  },
  {
   "is_class": false,
   "is_explicit": false,
   "module": "pandas.core",
   "module_short": "pandas.core",
   "name": "OpsMixin.query"
  },
  {
   "is_class": false,
   "is_explicit": false,
   "module": "pandas",
   "module_short": "pandas",
   "name": "OpsMixin.query"
  },
  {
   "is_class": false,
   "is_explicit": false,
   "module": "pandas.core.base",
   "module_short": "pandas.core.base",
   "name": "PandasObject.query"
  },
  {
   "is_class": false,
   "is_explicit": false,
   "module": "pandas.core",
   "module_short": "pandas.core",
   "name": "PandasObject.query"
  },
  {
   "is_class": false,
   "is_explicit": false,
   "module": "pandas",
   "module_short": "pandas",
   "name": "PandasObject.query"
  },
  {
   "is_class": false,
   "is_explicit": false,
   "module": "pandas.core.indexing",
   "module_short": "pandas.core.indexing",
   "name": "IndexingMixin.query"
  },
  {
   "is_class": false,
   "is_explicit": false,
   "module": "pandas.core",
   "module_short": "pandas.core",
   "name": "IndexingMixin.query"
  },
  {
   "is_class": false,
   "is_explicit": false,
   "module": "pandas",
   "module_short": "pandas",
   "name": "IndexingMixin.query"
  },
  {
   "is_class": false,
   "is_explicit": false,
   "module": "pandas.core.accessor",
   "module_short": "pandas.core.accessor",
   "name": "DirNamesMixin.query"
  },
  {
   "is_class": false,
   "is_explicit": false,
   "module": "pandas.core",
   "module_short": "pandas.core",
   "name": "DirNamesMixin.query"
  },
  {
   "is_class": false,
   "is_explicit": false,
   "module": "pandas",
   "module_short": "pandas",
   "name": "DirNamesMixin.query"
  }
 ],
 "results.to_string": [
  {
   "is_class": false,
   "is_explicit": false,
   "module": "pandas.core.frame",
   "module_short": "pandas.core.frame",
   "name": "DataFrame.to_string"
  },
  {
   "is_class": false,
   "is_explicit": false,
   "module": "pandas.core",
   "module_short": "pandas.core",
   "name": "DataFrame.to_string"
  },
  {
   "is_class": false,
   "is_explicit": false,
   "module": "pandas",
   "module_short": "pandas",
   "name": "DataFrame.to_string"
  },
  {
   "is_class": false,
   "is_explicit": false,
   "module": "pandas.core.generic",
   "module_short": "pandas.core.generic",
   "name": "NDFrame.to_string"
  },
  {
   "is_class": false,
   "is_explicit": false,
   "module": "pandas.core",
   "module_short": "pandas.core",
   "name": "NDFrame.to_string"
  },
  {
   "is_class": false,
   "is_explicit": false,
   "module": "pandas",
   "module_short": "pandas",
   "name": "NDFrame.to_string"
  },
  {
   "is_class": false,
   "is_explicit": false,
   "module": "pandas.core.arraylike",
   "module_short": "pandas.core.arraylike",
   "name": "OpsMixin.to_string"
  },
  {
   "is_class": false,
   "is_explicit": false,
   "module": "pandas.core",
   "module_short": "pandas.core",
   "name": "OpsMixin.to_string"
  },
  {
   "is_class": false,
   "is_explicit": false,
   "module": "pandas",
   "module_short": "pandas",
   "name": "OpsMixin.to_string"
  },
  {
   "is_class": false,
   "is_explicit": false,
   "module": "pandas.core.base",
   "module_short": "pandas.core.base",
   "name": "PandasObject.to_string"
  },
  {
   "is_class": false,
   "is_explicit": false,
   "module": "pandas.core",
   "module_short": "pandas.core",
   "name": "PandasObject.to_string"
  },
  {
   "is_class": false,
   "is_explicit": false,
   "module": "pandas",
   "module_short": "pandas",
   "name": "PandasObject.to_string"
  },
  {
   "is_class": false,
   "is_explicit": false,
   "module": "pandas.core.indexing",
   "module_short": "pandas.core.indexing",
   "name": "IndexingMixin.to_string"
  },
  {
   "is_class": false,
   "is_explicit": false,
   "module": "pandas.core",
   "module_short": "pandas.core",
   "name": "IndexingMixin.to_string"
  },
  {
   "is_class": false,
   "is_explicit": false,
   "module": "pandas",
   "module_short": "pandas",
   "name": "IndexingMixin.to_string"
  },
  {
   "is_class": false,
   "is_explicit": false,
   "module": "pandas.core.accessor",
   "module_short": "pandas.core.accessor",
   "name": "DirNamesMixin.to_string"
  },
  {
   "is_class": false,
   "is_explicit": false,
   "module": "pandas.core",
   "module_short": "pandas.core",
   "name": "DirNamesMixin.to_string"
  },
  {
   "is_class": false,
   "is_explicit": false,
   "module": "pandas",
   "module_short": "pandas",
   "name": "DirNamesMixin.to_string"
  }
 ],
 "roi": [
  {
   "is_class": false,
   "is_explicit": false,
   "module": "builtins",
   "module_short": "builtins",
   "name": "dict"
  }
 ],
 "rois": [
  {
   "is_class": false,
   "is_explicit": false,
   "module": "builtins",
   "module_short": "builtins",
   "name": "dict"
  }
 ],
 "rois.keys": [
  {
   "is_class": false,
   "is_explicit": false,
   "module": "builtins",
   "module_short": "builtins",
   "name": "builtin_function_or_method"
  }
 ],
 "rows": [
  {
   "is_class": false,
   "is_explicit": false,
   "module": "builtins",
   "module_short": "builtins",
   "name": "list"
  }
 ],
 "sns.catplot": [
  {
   "is_class": false,
   "is_explicit": false,
   "module": "builtins",
   "module_short": "builtins",
   "name": "function"
  },
  {
   "is_class": false,
   "is_explicit": false,
   "module": "seaborn",
   "module_short": "seaborn",
   "name": "catplot"
  }
 ],
 "sns.move_legend": [
  {
   "is_class": false,
   "is_explicit": false,
   "module": "builtins",
   "module_short": "builtins",
   "name": "function"
  },
  {
   "is_class": false,
   "is_explicit": false,
   "module": "seaborn",
   "module_short": "seaborn",
   "name": "move_legend"
  }
 ],
 "subj": [
  {
   "is_class": false,
   "is_explicit": false,
   "module": "builtins",
   "module_short": "builtins",
   "name": "str"
  }
 ],
 "tristan_rat": [
  {
   "is_class": false,
   "is_explicit": false,
   "module": "builtins",
   "module_short": "builtins",
   "name": "function"
  }
 ],
 "visit": [
  {
   "is_class": false,
   "is_explicit": false,
   "module": "builtins",
   "module_short": "builtins",
   "name": "str"
  }
 ]
}